LICENSE
README
setup.py
bin/stackeddag
stackeddag/__init__.py
stackeddag/core.py
stackeddag/graphviz.py
stackeddag/mxnet.py
stackeddag/tf.py
stackeddag.egg-info/PKG-INFO
stackeddag.egg-info/SOURCES.txt
stackeddag.egg-info/dependency_links.txt
stackeddag.egg-info/requires.txt
stackeddag.egg-info/top_level.txt