Metadata-Version: 2.1
Name: stackeddag
Version: 0.3.4
Summary: A visualization tool to show a ascii graph from Graphviz-Dot-file or Tensorflow
Home-page: https://github.com/junjihashimoto/py-stacked-dag
Author: Junji Hashimoto
Author-email: junji.hashimoto@gmail.com
License: MIT
Keywords: tensorflow tensor machine-learning graphviz ascii dag ml deep-learning neural-network
Platform: UNKNOWN
License-File: LICENSE
